greeklt/__init__.py
greeklt/capitalize.py
greeklt/convert_final_s.py
greeklt/greek_transliteration.py
greeklt/remove_accentuation.py
greek_language_tools-1.1.0.dist-info/LICENSE
greek_language_tools-1.1.0.dist-info/METADATA
greek_language_tools-1.1.0.dist-info/WHEEL
greek_language_tools-1.1.0.dist-info/top_level.txt
greek_language_tools-1.1.0.dist-info/RECORD
