Metadata-Version: 2.1
Name: greek-language-tools
Version: 1.1.0
Summary: A library with tools for easy Greek word transformations.
Author-email: John Zaras <john.zaras@yahoo.com>
Project-URL: Homepage, https://github.com/sinnec/greek-language-tools
Project-URL: Bug Tracker, https://github.com/sinnec/greek-language-tools/issues
Classifier: Programming Language :: Python :: 3
Classifier: License :: OSI Approved :: MIT License
Classifier: Operating System :: OS Independent
Requires-Python: >=3.7
License-File: LICENSE
